{
  "ch3_v16_te": [
    [
      58006,
      "{\"english\": \"1 Chronicles\", \"telugu\": \"దినవృత్తాంతములు మొదటి గ్రంథము\"}",
      3,
      16,
      "యెహోయాకీము కుమారులలో యెకొన్యా అను ఒకడుండెను, అతని కుమారుడు సిద్కియా.",
      "telugu"
    ],
    [
      58886,
      "{\"english\": \"1 Corinthians\", \"telugu\": \"1 కొరింథీయులకు\"}",
      3,
      16,
      "మీరు దేవుని ఆలయమై యున్నారనియు, దేవుని ఆత్మ మీలో నివసించుచున్నాడనియు మీరెరుగరా?",
      "telugu"
    ]
  ],
  "books_te": [
    [
      "{\"english\": \"1 Chronicles\", \"telugu\": \"దినవృత్తాంతములు మొదటి గ్రంథము\"}"
    ],
    [
      "{\"english\": \"1 Corinthians\", \"telugu\": \"1 కొరింథీయులకు\"}"
    ],
    [
      "{\"english\": \"1 John\", \"telugu\": \"1 యోహాను\"}"
    ],
    [
      "{\"english\": \"1 Kings\", \"telugu\": \"రాజులు మొదటి గ్రంథము\"}"
    ],
    [
      "{\"english\": \"1 Peter\", \"telugu\": \"1 పేతురు\"}"
    ]
  ]
}